galaxy/__init__.py
galaxy/py.typed
galaxy/files/__init__.py
galaxy/files/plugins.py
galaxy/files/uris.py
galaxy/files/sources/__init__.py
galaxy/files/sources/_pyfilesystem2.py
galaxy/files/sources/_rdm.py
galaxy/files/sources/anvil.py
galaxy/files/sources/azure.py
galaxy/files/sources/base64.py
galaxy/files/sources/basespace.py
galaxy/files/sources/dataverse.py
galaxy/files/sources/dropbox.py
galaxy/files/sources/drs.py
galaxy/files/sources/elabftw.py
galaxy/files/sources/ftp.py
galaxy/files/sources/galaxy.py
galaxy/files/sources/googlecloudstorage.py
galaxy/files/sources/googledrive.py
galaxy/files/sources/http.py
galaxy/files/sources/invenio.py
galaxy/files/sources/onedata.py
galaxy/files/sources/posix.py
galaxy/files/sources/remotezip.py
galaxy/files/sources/rspace.py
galaxy/files/sources/s3fs.py
galaxy/files/sources/ssh.py
galaxy/files/sources/temp.py
galaxy/files/sources/util.py
galaxy/files/sources/webdav.py
galaxy/files/sources/zenodo.py
galaxy/files/templates/__init__.py
galaxy/files/templates/manager.py
galaxy/files/templates/models.py
galaxy/files/templates/examples/__init__.py
galaxy/files/templates/examples/admin_secrets.yml
galaxy/files/templates/examples/admin_secrets_with_defaults.yml
galaxy/files/templates/examples/dropbox_client_secrets_explicit.yml
galaxy/files/templates/examples/dropbox_client_secrets_in_vault.yml
galaxy/files/templates/examples/onedata.yml
galaxy/files/templates/examples/production_aws_private_bucket.yml
galaxy/files/templates/examples/production_aws_public_bucket.yml
galaxy/files/templates/examples/production_azure.yml
galaxy/files/templates/examples/production_dropbox.yml
galaxy/files/templates/examples/production_ftp.yml
galaxy/files/templates/examples/production_google_drive.yml
galaxy/files/templates/examples/production_s3fs.yml
galaxy/files/templates/examples/production_webdav.yml
galaxy/files/templates/examples/s3fs_by_host_and_port.yml
galaxy/files/templates/examples/templating_override.yml
galaxy_files-25.0.3.dist-info/METADATA
galaxy_files-25.0.3.dist-info/WHEEL
galaxy_files-25.0.3.dist-info/top_level.txt
galaxy_files-25.0.3.dist-info/RECORD
